sentry_zendesk/__init__.py
sentry_zendesk/client.py
sentry_zendesk/plugin.py
sentry_zendesk/_version.py
sentry_zendesk-1.0.0.dist-info/top_level.txt
sentry_zendesk-1.0.0.dist-info/entry_points.txt
sentry_zendesk-1.0.0.dist-info/METADATA
sentry_zendesk-1.0.0.dist-info/DESCRIPTION.rst
sentry_zendesk-1.0.0.dist-info/metadata.json
sentry_zendesk-1.0.0.dist-info/WHEEL
sentry_zendesk-1.0.0.dist-info/RECORD
