Metadata-Version: 2.0
Name: sentry-zendesk
Version: 1.0.0
Summary: Plugin for Sentry which allows linking Zendesk tickets to Sentry issues
Home-page: https://github.com/ESSS/sentry-zendesk
Author: ESSS
Author-email: UNKNOWN
License: Apache
Platform: UNKNOWN
Classifier: Intended Audience :: Developers
Classifier: Intended Audience :: System Administrators
Classifier: License :: OSI Approved :: Apache Software License
Classifier: Operating System :: POSIX :: Linux
Classifier: Programming Language :: Python :: 2
Classifier: Programming Language :: Python :: 2.7
Classifier: Topic :: Software Development
Requires-Dist: sentry (>=8.11.0)
Requires-Dist: sentry-plugins (>=8.11.0)
